{
  "authority": "FAA",
  "part": "23",
  "section": "1301",
  "current_subpart": "Equipment",
  "canonical_title": "Function and installation.",
  "amendments": [
    {
      "designator": "23-0",
      "subpart_at_time": "Equipment",
      "title_at_amendment": "Function and installation.",
      "text": "(a) Each item of equipment essential for safe operation, including radio communication and navigation equipment, must-- (1) Adequately perform its intended function; (2) In the case of equipment other than radio communications and navigation equipment, function properly when installed; (3) In the case of radio communications and navigation equipment, be installed as prescribed in Sec. 23.1431; and (4) Where appropriate, be adequately labeled as to its identification, function, and operating limitations. (b) Whenever necessary, additional equipment that is installed as prescribed in the operating rules of this chapter, must meet the requirements of this section.",
      "federal_register_cite": "42 FR 36968",
      "source_url": "https://drs.faa.gov/browse/excelExternalWindow/BE5B26BBEDB26AF285256687006FEE83.0001",
      "actions": [
        {
          "type": "nprm",
          "reference": "64-17",
          "issued_on": "2064-03-25",
          "source_url": null,
          "notes": null
        },
        {
          "type": "final_rule",
          "reference": "4080",
          "issued_on": "2064-09-28",
          "source_url": null,
          "notes": null
        }
      ]
    },
    {
      "designator": "23-7",
      "subpart_at_time": "Equipment",
      "title_at_amendment": "Function and installation.",
      "text": "[(a) Each item of installed equipment essential for safe operation must-- (1) Be of a kind and design appropriate to its intended function; (2) If appropriate, be labeled as to its identification, function, or operating limitations, or any applicable combination of these factors; (3) Be installed according to limitations prescribed for that equipment and in compliance with Sec. 23.1431; and (4) Function properly when installed.] (b) Whenever necessary, additional equipment that is installed as prescribed in the operating rules of this chapter, must meet the requirements of this section.",
      "federal_register_cite": "42 FR 36968",
      "source_url": "https://drs.faa.gov/browse/excelExternalWindow/3660169A424EF91785256687007011D6.0001",
      "actions": [
        {
          "type": "nprm",
          "reference": "67-14",
          "issued_on": "2067-04-05",
          "source_url": null,
          "notes": null
        },
        {
          "type": "final_rule",
          "reference": "8083",
          "issued_on": "1969-08-01",
          "source_url": null,
          "notes": null
        }
      ]
    }
  ],
  "subject_group": "General"
}
