{
  "authority": "FAA",
  "part": "23",
  "section": "1501",
  "current_subpart": "Operating Limitations and Information",
  "canonical_title": "General.",
  "amendments": [
    {
      "designator": "23-0",
      "subpart_at_time": "Operating Limitations and Information",
      "title_at_amendment": "General.",
      "text": "(a) Each operating limitation upon which the type design is based must be made available to the pilot and other appropriate crewmembers. (b) Any information not covered in paragraph (a) of this section that is necessary for safety must be made available to the crewmembers. (c) Each operating limitation specified in Secs. 23.1505 through 23.1525, and each similar limitation must, if necessary for safety, be-- (1) Established for the airplane; and (2) Made available to the crewmembers as prescribed in Secs. 23.1541 through 23.1589. 64-17; Issued on 03/25/64. --> Link to eCFR --> NPRM ACTIONS: &nbsp; Notice of Proposed Rulemaking. Notice No. 64-17; Issued on 03/25/64. 4080; Issued on 09/28/64. --> Link to eCFR --> FINAL RULE ACTIONS: &nbsp; Final Rule. Docket No. 4080; Issued on 09/28/64.",
      "federal_register_cite": "43 FR 2319",
      "source_url": "https://drs.faa.gov/browse/excelExternalWindow/3EA6E8E386FB055E8525668700718E8C.0001"
    }
  ]
}
