{
  "authority": "CAA (FAA)",
  "part": "CAR 3",
  "section": "415",
  "current_subpart": "Engines and Propellers",
  "canonical_title": "Engines",
  "subject_group": "Powerplant Installations \u2013 Reciprocating Engines",
  "amendments": [
    {
      "designator": "CAR3-0",
      "subpart_at_time": "Engines and Propellers",
      "title_at_amendment": "Engines.",
      "text": "3.416 Propellers.\n3.417 Propeller vibration.\n3.418 Propeller pitch and speed. l1mlta-\ntlons.\n3.419 Speed limitations for fixed pItch\npropellers. g r 0 u n d adjustable\npitch propellers, and automati-\ncally varying pit c b propellers\nwhich cannot be controlled In\nflight.\n3.420 Speed and pitch limitations for con-\ntrollable pitch propellers without\nconstant speed controls.\n3.421 Variable pitch propellers With coo-\nstant speed controls.\n3.422 Propeller clearance.\nFUEL SYSTEM\n3.429 General.\nARRANGEMENT\n3.430 Fuel system arrangement.\n3.431 Multienglne fuel system arrangement.\n3.432 Pressure feed. arrangements.\nOPERATION\n3.433 Fuel flow rate.\n3.434 Fuel flow rate for gravity systems.\n3.435 Fuel flow rate for pump systems.\n3.436 Fuel flow rate for aux1l1ary fuel sys-\ntems and fuel transfer systems.\nSoc.\nS.437 Determination of unusable fuel sup-\nply and fuel system operation on\nlow fuel.\n3.438 Fuel system hot weather operation.\n3.439 Flow between Interconnected tanks.\n3.440\n3.441\n3.442\n3.443\n3.444\n3.445\n3.446\nFUEL TANKS\nGeneral.\nFuel tank tests.\nFuel tank installation.\nFuel tank expansion space.\nFuel tank sump.\nFuel tank filler connection.\nFuel tank vents and carburetor vapor\nvents.\n3.447-A Fuel tank vents.\n3.448 Fuel tank outlet.\nFUEL PUMPS\n3.449 Fuel pump and pump installation.\nLINES, FITTINGS, AND ACCESSORIES\n3.550 Fuel system Hnes. fittings. and acces-\nEories.\n3.651 Fuel \\'alves.\n3.552 FUel strainer.\nDRAINS AND INSTRUMENTS\n3.553 Fuel system drains.\n3.554 Fuel system Instruments.\nOIL SYSTEM\n3.561 all system.\n3.562 all cooling.\nOIL TANKS\n3.663 all tanks.\n3.564 au tank. tests.\n3.565 011 tank installation.\n3.566 au tank expansion space.",
      "federal_register_cite": "",
      "source_url": null
    }
  ]
}
